pingpy/__init__.py
pingpy/__main__.py
pingpy/main.py
pingpy-0.1.1.dist-info/METADATA
pingpy-0.1.1.dist-info/WHEEL
pingpy-0.1.1.dist-info/RECORD
