Metadata-Version: 2.3
Name: pingpy
Version: 0.1.1
Summary: A cross-platform Python wrapper around the `ping` utility.
Project-URL: Repository, https://github.com/redjax/pingpy
Author-email: redjax <no@none.com>
License: MIT
Requires-Python: >=3.11
